pyxtf/__init__.py
pyxtf/enumerations.py
pyxtf/xtf_ctypes.py
pyxtf/xtf_ctypes.pyi
pyxtf/xtf_io.py
pyxtf/xtf_util.py
pyxtf/vendors/__init__.py
pyxtf/vendors/kongsberg.py
pyxtf/vendors/kongsberg.pyi
pyxtf-1.4.2.dist-info/LICENSE
pyxtf-1.4.2.dist-info/METADATA
pyxtf-1.4.2.dist-info/WHEEL
pyxtf-1.4.2.dist-info/top_level.txt
pyxtf-1.4.2.dist-info/RECORD
