Metadata-Version: 2.1
Name: pyxtf
Version: 1.4.2
Summary: eXtended Triton Format (XTF) file interface
Home-page: https://github.com/oysstu/pyxtf
Author: Oystein Sture
Author-email: oysstu@gmail.com
License: MIT
Project-URL: Bug Tracker, https://github.com/oysstu/pyxtf/issues
Classifier: License :: OSI Approved :: MIT License
Classifier: Intended Audience :: Developers
Classifier: Intended Audience :: Other Audience
Classifier: Intended Audience :: Science/Research
Classifier: Natural Language :: English
Classifier: Topic :: Scientific/Engineering
Classifier: Programming Language :: Python :: 3 :: Only
License-File: LICENSE
Requires-Dist: numpy>=1.11
Provides-Extra: plotting
Requires-Dist: matplotlib>=1.5.1; extra == "plotting"
